Workbook

Sheet Premissas
A1: Premissas — editáveis (amarelo)
A3: Parâmetro | B3: Valor | C3: Observação
A4: Custo por separação (R$) | B4: 0.15 | C4: Demucs self-hosted em GPU serverless. Resíntese subiria p/ R$0,25-0,45.
A5: Infra por usuário ativo (R$/mês) | B5: 0.08 | C5: Servidor, banda, storage R2. CRESCE com a base de usuários.
A6: Taxa Asaas — fixa (R$) | B6: 0.49 | C6: Por cobrança recorrente.
A7: Taxa Asaas — percentual | B7: 0.0199 | C7: 1,99% sobre o valor.
A8: Utilização média da cota | B8: 0.5 | C8: Fração da cota que o usuário médio usa/mês.
A9: Usuários ativos por pessoa (capacidade) | B9: 2000 | C9: A cada N usuários, +1 pessoa.
A10: Custo por pessoa (R$/mês) | B10: 1000 | C10: Pró-labore/salário. Pessoal ESCALA em degraus.
A12: Preços (R$/mês)
A13: Free | B13: 0
A14: Pro | B14: 19.9
A15: ProBand (banda) | B15: 59.9
A16: FreeBand | B16: 0
A18: Cota de separação (por mês)
A19: Free | B19: 3
A20: Pro | B20: 20
A21: ProBand | B21: 40
A22: FreeBand | B22: 3

Sheet CustosFixos
A1: Custos fixos de estrutura (não escalam com usuários)
A3: Linha de custo | B3: R$/mês | C3: Observação
A4: Domínio + ferramentas | B4: 50 | C4: Domínio, e-mail, libs, monitoramento.
A5: Marketing / aquisição | B5: 0 | C5: Ads, criadores, parcerias (defina seu valor).
A6: Contábil / jurídico | B6: 0 | C6: Contador MEI/ME, revisão de termos.
A7: Total fixo estrutura | B7: =SUM(B4:B6) -> 50
A9: Pessoal NÃO entra aqui: é calculado por capacidade (Premissas) e escala com a base — ver Projecao.

Sheet Projecao
A1: Projeção mensal — ajuste os usuários ativos (amarelo)
A3: Plano | B3: Usuários | C3: Preço | D3: MRR | E3: Cota | F3: Util | G3: Separações | H3: Custo sep | I3: Infra/usu | J3: Taxa pgto | K3: Contribuição
A4: Free | B4: 1000 | C4: =Premissas!$B$13 -> 0 | D4: =B4*C4 -> 0 | E4: =Premissas!$B$19 -> 3 | F4: =Premissas!$B$8 -> 0.5 | G4: =B4*E4*F4 -> 1500 | H4: =G4*Premissas!$B$4 -> 225 | I4: =B4*Premissas!$B$5 -> 80 | J4: =IF(C4>0,B4*(Premissas!$B$6+C4*Premissas!$B$7),0) -> 0 | K4: =D4-H4-I4-J4 -> -305
A5: Pro | B5: 1 | C5: =Premissas!$B$14 -> 19.9 | D5: =B5*C5 -> 19.9 | E5: =Premissas!$B$20 -> 20 | F5: =Premissas!$B$8 -> 0.5 | G5: =B5*E5*F5 -> 10 | H5: =G5*Premissas!$B$4 -> 1.5 | I5: =B5*Premissas!$B$5 -> 0.08 | J5: =IF(C5>0,B5*(Premissas!$B$6+C5*Premissas!$B$7),0) -> 0.88601 | K5: =D5-H5-I5-J5 -> 17.43399
A6: ProBand | B6: 1 | C6: =Premissas!$B$15 -> 59.9 | D6: =B6*C6 -> 59.9 | E6: =Premissas!$B$21 -> 40 | F6: =Premissas!$B$8 -> 0.5 | G6: =B6*E6*F6 -> 20 | H6: =G6*Premissas!$B$4 -> 3 | I6: =B6*Premissas!$B$5 -> 0.08 | J6: =IF(C6>0,B6*(Premissas!$B$6+C6*Premissas!$B$7),0) -> 1.68201 | K6: =D6-H6-I6-J6 -> 55.13799
A7: FreeBand | B7: =B6*5 -> 5 | C7: =Premissas!$B$16 -> 0 | D7: =B7*C7 -> 0 | E7: =Premissas!$B$22 -> 3 | F7: =Premissas!$B$8 -> 0.5 | G7: =B7*E7*F7 -> 7.5 | H7: =G7*Premissas!$B$4 -> 1.125 | I7: =B7*Premissas!$B$5 -> 0.4 | J7: =IF(C7>0,B7*(Premissas!$B$6+C7*Premissas!$B$7),0) -> 0 | K7: =D7-H7-I7-J7 -> -1.525
A8: Total | B8: =SUM(B4:B7) -> 1007 | D8: =SUM(D4:D7) -> 79.8 | G8: =SUM(G4:G7) -> 1537.5 | H8: =SUM(H4:H7) -> 230.625 | I8: =SUM(I4:I7) -> 80.56 | J8: =SUM(J4:J7) -> 2.56802 | K8: =SUM(K4:K7) -> -233.95302
A10: ── Custos que escalam com a base ──
A11: Usuários totais | B11: =B8 -> 1007
A12: Pessoas necessárias (ROUNDUP usuários ÷ capacidade) | B12: =ROUNDUP(B11/Premissas!$B$9,0) -> 1
A13: Custo pessoal (R$/mês) | B13: =B12*Premissas!$B$10 -> 1000
A14: Custos fixos estrutura (R$/mês) | B14: =CustosFixos!$B$7 -> 50
A15: Custo TOTAL (variáveis + pessoal + fixo, R$/mês) | B15: =(H8+I8+J8)+B13+B14 -> 1363.753
A16: Receita total (MRR, R$/mês) | B16: =D8 -> 79.8
A17: LUCRO mensal (R$) | B17: =K8-B13-B14 -> -1283.953
A19: Cenário-base ilustrativo (~1.000 usuários). Pessoal escala em degraus: a cada 'capacidade' usuários, +1 pessoa — por isso o custo sobe com a base.

Sheet UnitEconomics
A1: Unit economics — margem de contribuição por assinante (antes de pessoal/fixo)
A3: Plano | B3: Preço | C3: Custo sep | D3: Infra | E3: Taxa | F3: Margem R$ | G3: Margem %
A4: Pro | B4: =Premissas!$B$14 -> 19.9 | C4: =Premissas!$B$20*Premissas!$B$8*Premissas!$B$4 -> 1.5 | D4: =Premissas!$B$5 -> 0.08 | E4: =Premissas!$B$6+B4*Premissas!$B$7 -> 0.88601 | F4: =B4-C4-D4-E4 -> 17.43399 | G4: =F4/B4 -> 0.8760799
A5: ProBand (banda + 5) | B5: =Premissas!$B$15 -> 59.9 | C5: =Premissas!$B$21*Premissas!$B$8*Premissas!$B$4+5*Premissas!$B$22*Premissas!$B$8*Premissas!$B$4 -> 4.125 | D5: =6*Premissas!$B$5 -> 0.48 | E5: =Premissas!$B$6+B5*Premissas!$B$7 -> 1.68201 | F5: =B5-C5-D5-E5 -> 53.61299 | G5: =F5/B5 -> 0.89504157
A7: Margem de contribuição = antes de pessoal e fixo de estrutura. Free/FreeBand só geram custo (subsídio).

Sheet PontoEquilibrio
A1: Ponto de equilíbrio e maximização de lucro
A4: Contribuição por usuário (base) — R$ | B4: =Projecao!K8/Projecao!B8 -> -0.23232673
A5: Custo de pessoal por usuário — R$ | B5: =Premissas!$B$10/Premissas!$B$9 -> 0.5
A6: Margem líquida por usuário — R$ | B6: =B4-B5 -> -0.73232673
A7: Custos fixos de estrutura — R$/mês | B7: =CustosFixos!$B$7 -> 50
A8: Custo do 1º colaborador — R$/mês | B8: =Premissas!$B$10 -> 1000
A9: Usuários no equilíbrio (assumindo 1 pessoa) | B9: =(B7+B8)/B4 -> -4519.4971
A10: → Pagantes no equilíbrio (mesma composição) | B10: =B9*(Projecao!B5+Projecao!B6)/Projecao!B8 -> -8.9761611
A11: Lucro no cenário-base — R$/mês | B11: =Projecao!B17 -> -1283.953
A14: Escala de crescimento — custo de pessoal sobe em degraus com os usuários
A15: Multipl. | B15: Usuários | C15: Pagantes | D15: MRR | E15: Contribuição | F15: Pessoas | G15: Pessoal | H15: Fixo | I15: Lucro
A16: 0.5 | B16: =A16*Projecao!$B$8 -> 503.5 | C16: =A16*(Projecao!$B$5+Projecao!$B$6) -> 1 | D16: =A16*Projecao!$D$8 -> 39.9 | E16: =A16*Projecao!$K$8 -> -116.97651 | F16: =ROUNDUP(B16/Premissas!$B$9,0) -> 1 | G16: =F16*Premissas!$B$10 -> 1000 | H16: =CustosFixos!$B$7 -> 50 | I16: =E16-G16-H16 -> -1166.9765
A17: 1 | B17: =A17*Projecao!$B$8 -> 1007 | C17: =A17*(Projecao!$B$5+Projecao!$B$6) -> 2 | D17: =A17*Projecao!$D$8 -> 79.8 | E17: =A17*Projecao!$K$8 -> -233.95302 | F17: =ROUNDUP(B17/Premissas!$B$9,0) -> 1 | G17: =F17*Premissas!$B$10 -> 1000 | H17: =CustosFixos!$B$7 -> 50 | I17: =E17-G17-H17 -> -1283.953
A18: 2 | B18: =A18*Projecao!$B$8 -> 2014 | C18: =A18*(Projecao!$B$5+Projecao!$B$6) -> 4 | D18: =A18*Projecao!$D$8 -> 159.6 | E18: =A18*Projecao!$K$8 -> -467.90604 | F18: =ROUNDUP(B18/Premissas!$B$9,0) -> 2 | G18: =F18*Premissas!$B$10 -> 2000 | H18: =CustosFixos!$B$7 -> 50 | I18: =E18-G18-H18 -> -2517.906
A19: 3 | B19: =A19*Projecao!$B$8 -> 3021 | C19: =A19*(Projecao!$B$5+Projecao!$B$6) -> 6 | D19: =A19*Projecao!$D$8 -> 239.4 | E19: =A19*Projecao!$K$8 -> -701.85906 | F19: =ROUNDUP(B19/Premissas!$B$9,0) -> 2 | G19: =F19*Premissas!$B$10 -> 2000 | H19: =CustosFixos!$B$7 -> 50 | I19: =E19-G19-H19 -> -2751.8591
A20: 5 | B20: =A20*Projecao!$B$8 -> 5035 | C20: =A20*(Projecao!$B$5+Projecao!$B$6) -> 10 | D20: =A20*Projecao!$D$8 -> 399 | E20: =A20*Projecao!$K$8 -> -1169.7651 | F20: =ROUNDUP(B20/Premissas!$B$9,0) -> 3 | G20: =F20*Premissas!$B$10 -> 3000 | H20: =CustosFixos!$B$7 -> 50 | I20: =E20-G20-H20 -> -4219.7651
A21: 10 | B21: =A21*Projecao!$B$8 -> 10070 | C21: =A21*(Projecao!$B$5+Projecao!$B$6) -> 20 | D21: =A21*Projecao!$D$8 -> 798 | E21: =A21*Projecao!$K$8 -> -2339.5302 | F21: =ROUNDUP(B21/Premissas!$B$9,0) -> 6 | G21: =F21*Premissas!$B$10 -> 6000 | H21: =CustosFixos!$B$7 -> 50 | I21: =E21-G21-H21 -> -8389.5302
A23: Leitura: a contribuição cresce linear com a base, mas o pessoal sobe em degraus (a cada 'capacidade' usuários, +1 pessoa). Lucro máximo vem de: (1) manter cada degrau de pessoal bem preenchido antes de contratar o próximo, (2) elevar a conversão free->pago, (3) proteger o preço do plano banda. O custo de separação é pequeno — não é a alavanca.

Sheet Comparativo_Moises
A1: Comparativo com Moises — norte de posicionamento (não é competição direta)
B3: Moises | C3: backingtrack.store
A4: Plano gratuito | B4: 5 separações/mês; export limitado a 1 min | C4: Free: 3 separações/mês; sem limite de export
A5: Plano de entrada | B5: Premium ~R$16,90/mês (R$9,90 obs. jul/2026) Separação ILIMITADA | C5: Pro R$19,90/mês 20 separações/mês + colaboração
A6: Plano superior | B6: Pro ~R$29/mês — produção (VST, mix, master) | C6: ProBand R$59,90/mês — banda até 6 (líder + 5)
A7: Foco do produto | B7: Prática/produção individual | C7: Colaboração de banda + Modo Performance (palco)
A8: Separação de áudio | B8: Commodity ilimitada barata (força deles) | C8: Cota limitada — não é o nosso eixo de valor
A9: Nosso diferencial | B9: — | C9: Setlist compartilhado, cifra validada pela comunidade, stems por integrante, palco
A12: Ponto de equilíbrio: banda vs. cada um pagando Moises
A13: Integrantes | B13: Custo se cada um pagar Moises | C13: Plano ProBand (fixo)
A14: 4 | B14: =A14*16.9 -> 67.6 | C14: =Premissas!$B$15 -> 59.9
A15: 6 | B15: =A15*16.9 -> 101.4 | C15: =Premissas!$B$15 -> 59.9
A16: 8 | B16: =A16*16.9 -> 135.2 | C16: =Premissas!$B$15 -> 59.9
A17: 12 | B17: =A17*16.9 -> 202.8 | C17: =Premissas!$B$15 -> 59.9
A19: Moises Premium R$16,90 (listagem pública jul/2026). A partir de ~4 integrantes o plano banda já sai mais barato que assinaturas individuais.
